translator/__init__.py
translator/api_tradutor.py
trad_pt-0.4.dist-info/LICENSE
trad_pt-0.4.dist-info/METADATA
trad_pt-0.4.dist-info/WHEEL
trad_pt-0.4.dist-info/top_level.txt
trad_pt-0.4.dist-info/RECORD
