Metadata-Version: 2.1
Name: trad-pt
Version: 0.4
Summary: Translate words or phrases from English to Portuguese
Author-email: Fabio Zanetti <fczanetti@hotmail.com>
License: GNU AFFERO GENERAL PUBLIC LICENSE
Project-URL: Repository, https://github.com/Zanettifabio/translate
Keywords: portuguese,translation
Classifier: Development Status :: 1 - Planning
Classifier: Intended Audience :: Education
Classifier: License :: OSI Approved :: GNU Affero General Public License v3
Classifier: Programming Language :: Python :: 3.11
Requires-Python: >=3.11
License-File: LICENSE
Requires-Dist: translators
